dataprep_lite/__init__.py
dataprep_lite/cleaning/__init__.py
dataprep_lite/cleaning/data_types.py
dataprep_lite/cleaning/duplicates.py
dataprep_lite/cleaning/missing_values.py
dataprep_lite/cleaning/outliers.py
dataprep_lite/cleaning/text_cleaning.py
dataprep_lite/core/__init__.py
dataprep_lite/core/base_transformer.py
dataprep_lite/core/pipeline.py
dataprep_lite/core/utils.py
dataprep_lite/preprocessing/__init__.py
dataprep_lite/preprocessing/discretization.py
dataprep_lite/preprocessing/encoding.py
dataprep_lite/preprocessing/feature_creation.py
dataprep_lite/preprocessing/scaling.py
dataprep_lite-1.0.3.dist-info/METADATA
dataprep_lite-1.0.3.dist-info/WHEEL
dataprep_lite-1.0.3.dist-info/top_level.txt
dataprep_lite-1.0.3.dist-info/RECORD
